pyreaper/__init__.py
pyreaper-0.0.4.dist-info/METADATA
pyreaper-0.0.4.dist-info/RECORD
pyreaper-0.0.4.dist-info/WHEEL
pyreaper-0.0.4.dist-info/top_level.txt
