Metadata-Version: 2.1
Name: pyreaper
Version: 0.0.4
Summary: A python wrapper for REAPER (Robust Epoch And Pitch EstimatoR)
Home-page: https://github.com/r9y9/pyreaper
Author: Ryuichi Yamamoto
Author-email: zryuichi@gmail.com
License: MIT
Keywords: REAPER
Platform: UNKNOWN
Classifier: Operating System :: POSIX
Classifier: Operating System :: Unix
Classifier: Operating System :: MacOS
Classifier: Programming Language :: Cython
Classifier: Programming Language :: Python
Classifier: Programming Language :: Python :: 2
Classifier: Programming Language :: Python :: 2.7
Classifier: Programming Language :: Python :: 3
Classifier: Programming Language :: Python :: 3.4
Classifier: Programming Language :: Python :: 3.5
Classifier: License :: OSI Approved :: MIT License
Classifier: Topic :: Scientific/Engineering
Classifier: Topic :: Software Development
Classifier: Intended Audience :: Science/Research
Classifier: Intended Audience :: Developers
Provides-Extra: develop
Provides-Extra: test
Requires-Dist: numpy (>=1.8.0)
Provides-Extra: develop
Requires-Dist: cython (>=0.21.0); extra == 'develop'
Provides-Extra: test
Requires-Dist: nose; extra == 'test'
Requires-Dist: scipy; extra == 'test'
